README.md
setup.cfg
setup.py
sdc_dp_helpers/__init__.py
sdc_dp_helpers/base_readers.py
sdc_dp_helpers/base_writer.py
sdc_dp_helpers/base_writers.py
sdc_dp_helpers.egg-info/PKG-INFO
sdc_dp_helpers.egg-info/SOURCES.txt
sdc_dp_helpers.egg-info/dependency_links.txt
sdc_dp_helpers.egg-info/requires.txt
sdc_dp_helpers.egg-info/top_level.txt
sdc_dp_helpers/api_utilities/__init_.py
sdc_dp_helpers/api_utilities/data_managers.py
sdc_dp_helpers/api_utilities/date_managers.py
sdc_dp_helpers/api_utilities/exceptions.py
sdc_dp_helpers/api_utilities/file_managers.py
sdc_dp_helpers/api_utilities/retry_managers.py
sdc_dp_helpers/api_utilities/tracking_metadata.py
sdc_dp_helpers/azure/__init__.py
sdc_dp_helpers/azure/readers.py
sdc_dp_helpers/azure/writers.py
sdc_dp_helpers/facebook/__init__.py
sdc_dp_helpers/facebook/readers.py
sdc_dp_helpers/facebook/writers.py
sdc_dp_helpers/falcon/__init__.py
sdc_dp_helpers/falcon/falcon_sdk.py
sdc_dp_helpers/falcon/readers.py
sdc_dp_helpers/falcon/writers.py
sdc_dp_helpers/ftp/__init__.py
sdc_dp_helpers/ftp/readers.py
sdc_dp_helpers/ftp/writers.py
sdc_dp_helpers/google_ads/__init__.py
sdc_dp_helpers/google_ads/generate_refresh_token.py
sdc_dp_helpers/google_ads/readers.py
sdc_dp_helpers/google_ads/writers.py
sdc_dp_helpers/google_analytics/__init__.py
sdc_dp_helpers/google_analytics/config_managers.py
sdc_dp_helpers/google_analytics/readers.py
sdc_dp_helpers/google_analytics/utils.py
sdc_dp_helpers/google_analytics/writers.py
sdc_dp_helpers/google_analytics_v4/__init__.py
sdc_dp_helpers/google_analytics_v4/readers.py
sdc_dp_helpers/google_analytics_v4/writers.py
sdc_dp_helpers/google_big_query/__init__.py
sdc_dp_helpers/google_big_query/readers.py
sdc_dp_helpers/google_big_query/writers.py
sdc_dp_helpers/google_knowledge_graph/__init__.py
sdc_dp_helpers/google_knowledge_graph/gkg_sdk.py
sdc_dp_helpers/google_knowledge_graph/readers.py
sdc_dp_helpers/google_knowledge_graph/writers.py
sdc_dp_helpers/google_knowledge_graph_v1/__init__.py
sdc_dp_helpers/google_knowledge_graph_v1/readers.py
sdc_dp_helpers/google_knowledge_graph_v1/writers.py
sdc_dp_helpers/google_postmaster_tools/__init__.py
