Metadata-Version: 2.1
Name: sdc-dp-helpers
Version: 1.3.90
Summary: A module for developing data pipelines from external api's and on ETL like services
Home-page: http://github.com/RingierIMU/sdc-dataPipeline-helpers
Author: Ringier South Africa
Author-email: tools@ringier.co.za
License: UNKNOWN
Download-URL: https://github.com/RingierIMU/sdc-global-dataPipeline-helpers/archive/v1.3.90.zip
Keywords: pip,datapipeline,helpers
Platform: UNKNOWN
Provides-Extra: pyspark
